xkcd/__init__.py
xkcd/client.py
xkcd/comic.py
xkcd/errors.py
pyxkcd-0.1.0.dist-info/LICENSE
pyxkcd-0.1.0.dist-info/METADATA
pyxkcd-0.1.0.dist-info/WHEEL
pyxkcd-0.1.0.dist-info/top_level.txt
pyxkcd-0.1.0.dist-info/RECORD
