Metadata-Version: 2.1
Name: pyxkcd
Version: 0.1.0
Summary: A simple, easy-to-use xkcd API wrapper!
License: MIT License
Project-URL: Homepage, https://github.com/SomeHybrid/xkcd.py
Keywords: xkcd,api,api wrapper
Classifier: Framework :: AsyncIO
Classifier: Programming Language :: Python :: 3
Classifier: Topic :: System :: Networking
Requires-Python: >=3.7
License-File: LICENSE
Requires-Dist: httpx
Requires-Dist: importlib-metadata ; python_version >= "3.7"
